systemadmin/__init__.py
systemadmin/database.py
systemadmin/files.py
systemadmin-0.1.0.dist-info/WHEEL
systemadmin-0.1.0.dist-info/METADATA
systemadmin-0.1.0.dist-info/RECORD
