Metadata-Version: 2.1
Name: systemadmin
Version: 0.1.0
Summary: 
Author: Yassine
Requires-Python: >=3.8,<4.0
Classifier: Programming Language :: Python :: 3
Classifier: Programming Language :: Python :: 3.10
Classifier: Programming Language :: Python :: 3.8
Classifier: Programming Language :: Python :: 3.9
Requires-Dist: configparser (>=5.2.0,<6.0.0)
Requires-Dist: pandas (>=1.4.2,<2.0.0)
